mg/__init__.py
mg-0.0.2.dist-info/WHEEL
mg-0.0.2.dist-info/METADATA
mg-0.0.2.dist-info/RECORD
