Metadata-Version: 2.1
Name: mg
Version: 0.0.2
Summary: Machine Learning Extensions
Author: chkoar
Author-email: chkoar@users.noreply.github.com
Requires-Python: >=3.7,<4.0
Classifier: Programming Language :: Python :: 3
Classifier: Programming Language :: Python :: 3.7
Classifier: Programming Language :: Python :: 3.8
Requires-Dist: dagging (>=0.2.2,<0.3.0)
Requires-Dist: pytest-cov (>=2.11.1,<3.0.0)
Requires-Dist: scikit-learn (>=0.23,<0.24)
Requires-Dist: vfi (>=0.1.1,<0.2.0)
